{
  "id": "a2e5e403-7121-48b9-837a-b93a944ccd29",
  "label": "Apartement Door",
  "type": "DOOR",
  "tile_id": [
    "4a1d3474-7322-48d5-859f-8d9f50f479b9"
  ],
  "scope": {
    "component": [
      "home",
      "door",
      "apartement_door"
    ]
  },
  "placement_config": {
    "location_id": "ddc5097e-1018-443d-b288-e27e3a247e5d",
    "transformation_frame_id": "apartement_door",
    "position": {
      "translation": {
        "x": 2.718,
        "y": -0.125,
        "z": 0.0
      },
      "rotation": {
        "qw": 1.0,
        "qx": 0.0,
        "qy": 0.0,
        "qz": 0.0
      }
    },
    "shape": {
      "floor": [
        {
          "x": 0.0,
          "y": 0.0,
          "z": 0.0
        },
        {
          "x": 0.0,
          "y": 0.125,
          "z": 0.0
        },
        {
          "x": 0.889,
          "y": 0.125,
          "z": 0.0
        },
        {
          "x": 0.889,
          "y": 0.0,
          "z": 0.0
        }
      ]
    }
  },
  "meta_config": {}
}