{
  "id": "654c83c1-59f9-4ebc-b2e1-0874b0e53853",
  "label": "Standby",
  "type": "SCENE",
  "placement_config": {
    "location_id": "ddc5097e-1018-443d-b288-e27e3a247e5d",
    "transformation_frame_id": "Standby",
    "shape": {}
  },
  "scope": {
    "component": [
      "home",
      "scene",
      "standby"
    ]
  },
  "service_config": [
    {
      "binding_config": {
        "meta_config": {}
      },
      "unit_id": "654c83c1-59f9-4ebc-b2e1-0874b0e53853",
      "service_description": {
        "service_template_id": "f75053d2-7345-4928-ade6-eb3b4486ced9",
        "type": "ACTIVATION_STATE_SERVICE",
        "pattern": "OPERATION",
        "meta_config": {}
      },
      "meta_config": {}
    },
    {
      "binding_config": {
        "meta_config": {}
      },
      "unit_id": "654c83c1-59f9-4ebc-b2e1-0874b0e53853",
      "service_description": {
        "service_template_id": "f75053d2-7345-4928-ade6-eb3b4486ced9",
        "type": "ACTIVATION_STATE_SERVICE",
        "meta_config": {}
      },
      "meta_config": {}
    }
  ],
  "meta_config": {},
  "enabling_state": {
    "value": "ENABLED"
  },
  "scene_config": {
    "required_service_state_description": [
      {
        "unit_id": "ddc5097e-1018-443d-b288-e27e3a247e5d",
        "service_type": "POWER_STATE_SERVICE",
        "unit_type": "UNKNOWN",
        "service_attribute_type": "rst.domotic.state.PowerStateType$PowerState",
        "service_attribute": "{\"value\": \"OFF\",\"timestamp\": {\"time\": 1498574755814000}}"
      },
      {
        "unit_id": "f1397800-9741-401d-a46f-8bf139c12e92",
        "service_type": "POWER_STATE_SERVICE",
        "unit_type": "UNKNOWN",
        "service_attribute_type": "rst.domotic.state.PowerStateType$PowerState",
        "service_attribute": "{\"value\": \"OFF\",\"timestamp\": {\"time\": 1498574755813000}}"
      },
      {
        "unit_id": "98acc701-87b9-4cf2-b79b-3eb6c166e2fe",
        "service_type": "ACTIVATION_STATE_SERVICE",
        "unit_type": "UNKNOWN",
        "service_attribute_type": "rst.domotic.state.ActivationStateType$ActivationState",
        "service_attribute": "{\"value\": \"DEACTIVE\"}"
      },
      {
        "unit_id": "de6a3463-5a99-4162-851c-b535a26b6de8",
        "service_type": "POWER_STATE_SERVICE",
        "unit_type": "UNKNOWN",
        "service_attribute_type": "rst.domotic.state.PowerStateType$PowerState",
        "service_attribute": "{\"value\": \"OFF\",\"timestamp\": {\"time\": 1498574755814000}}"
      },
      {
        "unit_id": "804542df-aebc-42cb-82ef-f03a97c96bf8",
        "service_type": "POWER_STATE_SERVICE",
        "unit_type": "UNKNOWN",
        "service_attribute_type": "rst.domotic.state.PowerStateType$PowerState",
        "service_attribute": "{\"value\": \"OFF\",\"timestamp\": {\"time\": 1498574747051000}}"
      },
      {
        "unit_id": "f7d09b74-2f08-46ae-b3b9-c1f6fc8c8ed2",
        "service_type": "POWER_STATE_SERVICE",
        "unit_type": "UNKNOWN",
        "service_attribute_type": "rst.domotic.state.PowerStateType$PowerState",
        "service_attribute": "{\"value\": \"OFF\",\"timestamp\": {\"time\": 1498574755815000}}"
      },
      {
        "unit_id": "bc243f30-f924-4348-b48e-2328aeb39da1",
        "service_type": "POWER_STATE_SERVICE",
        "unit_type": "UNKNOWN",
        "service_attribute_type": "rst.domotic.state.PowerStateType$PowerState",
        "service_attribute": "{\"value\": \"OFF\",\"timestamp\": {\"time\": 1498574755814000}}"
      },
      {
        "unit_id": "6f6dce7d-e959-49ff-9bf9-6b15dcde3082",
        "service_type": "POWER_STATE_SERVICE",
        "unit_type": "UNKNOWN",
        "service_attribute_type": "rst.domotic.state.PowerStateType$PowerState",
        "service_attribute": "{\"value\": \"OFF\",\"timestamp\": {\"time\": 1498574747052000}}"
      }
    ]
  }
}