{
  "id": "08e54371-ed6d-4d87-9328-7a9e2c82666f",
  "unit_template_config_id": "Fibaro_FGMS-001_TEMPERATURE_SENSOR_0",
  "label": "Entrance",
  "alias": [
    "TemperatureSensor-11"
  ],
  "unit_host_id": "d75030ec-82bd-42d7-9960-3ff2bbd21965",
  "type": "TEMPERATURE_SENSOR",
  "placement_config": {
    "location_id": "511adfec-43ed-47f5-bd4d-28f46dc1b5a4",
    "transformation_frame_id": "Control_Entrance"
  },
  "scope": {
    "component": [
      "home",
      "control",
      "temperaturesensor",
      "entrance"
    ]
  },
  "bound_to_unit_host": true,
  "service_config": [
    {
      "binding_config": {
        "binding_id": "OPENHAB",
        "meta_config": {
          "entry": [
            {
              "key": "OPENHAB_BINDING_ITEM_ID",
              "value": "Motion_Sensor__home_control__TemperatureSensor__Entrance__TemperatureStateService"
            }
          ]
        }
      },
      "unit_id": "08e54371-ed6d-4d87-9328-7a9e2c82666f",
      "service_description": {
        "service_template_id": "0512aab5-78cf-4464-b699-078f6f3dfdc9",
        "type": "TEMPERATURE_STATE_SERVICE",
        "pattern": "PROVIDER"
      },
      "meta_config": {}
    },
    {
      "binding_config": {
        "binding_id": "OPENHAB",
        "meta_config": {
          "entry": [
            {
              "key": "OPENHAB_BINDING_ITEM_ID",
              "value": "Motion_Sensor__home_control__TemperatureSensor__Entrance__TemperatureAlarmStateService"
            }
          ]
        }
      },
      "unit_id": "08e54371-ed6d-4d87-9328-7a9e2c82666f",
      "service_description": {
        "service_template_id": "14f52fce-8ec0-4f9d-8279-47547381473a",
        "type": "TEMPERATURE_ALARM_STATE_SERVICE",
        "pattern": "PROVIDER"
      },
      "meta_config": {}
    }
  ],
  "meta_config": {},
  "enabling_state": {
    "value": "ENABLED"
  }
}