{
  "id": "a60d810a-1045-4d64-846a-d0a1afb11d07",
  "unit_template_config_id": "Gira_429496730210000_BUTTON_4",
  "label": "learnperson",
  "unit_host_id": "d9e491b1-27b3-4736-9ce0-c52476e827d3",
  "type": "BUTTON",
  "placement_config": {
    "location_id": "4a1d3474-7322-48d5-859f-8d9f50f479b9",
    "transformation_frame_id": "learnperson",
    "position": {
      "translation": {
        "x": 0.0,
        "y": 0.0,
        "z": 0.0
      },
      "rotation": {
        "qw": 1.0,
        "qx": 0.0,
        "qy": 0.0,
        "qz": 0.0
      }
    }
  },
  "scope": {
    "component": [
      "home",
      "wardrobe",
      "button",
      "learnperson"
    ]
  },
  "bound_to_unit_host": true,
  "service_config": [
    {
      "binding_config": {
        "binding_id": "OPENHAB",
        "meta_config": {
          "entry": [
            {
              "key": "OPENHAB_BINDING_CONFIG",
              "value": "1/2/16"
            },
            {
              "key": "OPENHAB_BINDING_ITEM_ID",
              "value": "Gira_5133__home_wardrobe__Button__learnperson__ButtonStateService"
            }
          ]
        }
      },
      "unit_id": "a60d810a-1045-4d64-846a-d0a1afb11d07",
      "service_template": {
        "type": "BUTTON_STATE_SERVICE",
        "pattern": "PROVIDER"
      },
      "meta_config": {}
    }
  ],
  "meta_config": {},
  "enabling_state": {
    "value": "ENABLED"
  }
}