{
  "id": "c004ba7b-cf51-43f3-b470-c60e5a56bf99",
  "unit_template_config_id": "e18d2b16-1969-4e5b-b40c-8b255c2cdb8c_VIDEO_RGB_SOURCE_0",
  "label": "Kinect atl",
  "unit_host_id": "6678a48f-05a1-47f1-b962-35227c396675",
  "type": "VIDEO_RGB_SOURCE",
  "placement_config": {
    "location_id": "81b9efa4-2dc9-432e-b47c-1d73021ff0f3",
    "transformation_frame_id": "Kinect_atl",
    "position": {
      "translation": {
        "x": 1.226136533322924,
        "y": 5.456889238839775,
        "z": 0.43322136637659536
      },
      "rotation": {
        "qw": 0.8958949628775044,
        "qx": 0.4442507136736852,
        "qy": 0.0017807478619116814,
        "qz": -0.0032168040333902543
      }
    }
  },
  "scope": {
    "component": [
      "home",
      "living",
      "videorgbsource",
      "kinect_atl"
    ]
  },
  "bound_to_unit_host": true,
  "enabling_state": {
    "value": "ENABLED"
  }
}