{
  "id": "d09c4086-89fc-4b22-9196-2d458bb9d500",
  "unit_template_config_id": "Gira_429496730250000_BUTTON_1",
  "label": "Button 2 ",
  "unit_host_id": "a0e7ef4c-8011-4b61-963f-26f9e716d3cd",
  "type": "BUTTON",
  "placement_config": {
    "location_id": "f44ad3f8-25f4-44f9-adaa-384676b361a6",
    "transformation_frame_id": "Button_2_",
    "position": {
      "translation": {
        "x": 0.0,
        "y": 0.0,
        "z": 0.0
      },
      "rotation": {
        "qw": 1.0,
        "qx": 0.0,
        "qy": 0.0,
        "qz": 0.0
      }
    },
    "shape": {}
  },
  "scope": {
    "component": [
      "home",
      "bath",
      "button",
      "button_2_"
    ]
  },
  "bound_to_unit_host": true,
  "service_config": [
    {
      "binding_config": {
        "binding_id": "OPENHAB",
        "meta_config": {
          "entry": [
            {
              "key": "OPENHAB_BINDING_CONFIG",
              "value": "3/2/1"
            },
            {
              "key": "OPENHAB_BINDING_ITEM_ID",
              "value": "Gira_5142__home_bath__Button__Button_2___ButtonStateService"
            }
          ]
        }
      },
      "unit_id": "d09c4086-89fc-4b22-9196-2d458bb9d500",
      "service_template": {
        "type": "BUTTON_STATE_SERVICE",
        "pattern": "PROVIDER"
      },
      "meta_config": {}
    }
  ],
  "meta_config": {},
  "enabling_state": {
    "value": "ENABLED"
  }
}